burp_reports/VERSION
burp_reports/__init__.py
burp_reports/__main__.py
burp_reports/backends/__init__.py
burp_reports/backends/burpui_api.py
burp_reports/data/notes.md
burp_reports/data/test_inventory.csv
burp_reports/defaults/__init__.py
burp_reports/defaults/default_config.py
burp_reports/defaults/default_data_structure.py
burp_reports/dummy/__init__.py
burp_reports/dummy/burpui_api_translate_dummy.py
burp_reports/dummy/burpui_dummy_api.py
burp_reports/dummy/notusedyet/burpui_dummy_clients.py
burp_reports/interfaces/__init__.py
burp_reports/interfaces/burpui_api_interface.py
burp_reports/interfaces/burpui_api_translate.py
burp_reports/lib/__init__.py
burp_reports/lib/check_readme.py
burp_reports/lib/configs.py
burp_reports/lib/email.py
burp_reports/lib/files.py
burp_reports/lib/humanize.py
burp_reports/lib/imap.py
burp_reports/lib/is_up.py
burp_reports/lib/txt.py
burp_reports/lib/urlget.py
burp_reports/reports/__init__.py
burp_reports/reports/clients_reports.py
burp_reports/tests/__init__.py
burp_reports/tests/test_1_imap.py
burp_reports/tests/test_burpui_demo.py
burp_reports/tests/test_check_readme.py
burp_reports/tests/test_cli.py
burp_reports/tests/test_clients_dummy.py
burp_reports/tests/test_default_config.py
burp_reports/tests/test_dummy_api.py
burp_reports/tests/test_email.py
burp_reports/tests/test_inventory.py
burp_reports/tests/test_isup.py
burp_reports/tests/test_parser.py
burp_reports/tests/test_reports.py
burp_reports/tests/test_txt.py
burp_reports/tests/test_url.py
burp_reports-1.4.2.data/data/VERSION/VERSION
burp_reports-1.4.2.dist-info/DESCRIPTION.rst
burp_reports-1.4.2.dist-info/METADATA
burp_reports-1.4.2.dist-info/RECORD
burp_reports-1.4.2.dist-info/WHEEL
burp_reports-1.4.2.dist-info/entry_points.txt
burp_reports-1.4.2.dist-info/metadata.json
burp_reports-1.4.2.dist-info/top_level.txt
