Metadata-Version: 2.0
Name: burp-reports
Version: 1.4.2
Summary: Burp reports package
Home-page: https://github.com/pablodav/burp_server_reports
Author: Pablo Estigarribia
Author-email: pablodav@gmail.com
License: BSD3
Platform: UNKNOWN
Classifier: Development Status :: 5 - Production/Stable
Classifier: Intended Audience :: System Administrators
Classifier: License :: OSI Approved :: MIT License
Classifier: Programming Language :: Python :: 3
Classifier: Programming Language :: Python :: 3 :: Only
Classifier: Topic :: System :: Archiving :: Backup
Requires-Dist: arrow (>=0.12.1)
Requires-Dist: invpy-libs (>=0.4.2)
Requires-Dist: jinja2 (>=2.8)
Requires-Dist: pyzmail36
Requires-Dist: requests (>=2.19.1)
Requires-Dist: requests-cache (>=0.4.13)
Requires-Dist: rstcheck
Requires-Dist: urllib3 (>=1.23)
Requires-Dist: validators
